README.md
setup.cfg
setup.py
src/_pydt/__init__.py
src/envutil/__init__.py
src/envutil/core/__init__.py
src/envutil/core/config_var.py
src/envutil/core/constants.py
src/envutil/core/core.py
src/envutil/core/env_utils.py
src/envutil/core/exceptions.py
src/envutil/core/main.py
src/pyutilbox.egg-info/PKG-INFO
src/pyutilbox.egg-info/SOURCES.txt
src/pyutilbox.egg-info/dependency_links.txt
src/pyutilbox.egg-info/requires.txt
src/pyutilbox.egg-info/top_level.txt