Metadata-Version: 2.1
Name: pyutilbox
Version: 0.4
Summary: A simple Package to load & parse configuration to diffrent datatypes
Home-page: https://github.com/rionzz-inc/pyutilbox
Author: Prakash Leon Mishra
Author-email: dev.leonmishra@gmail.com
License: MIT
Project-URL: Bug Tracker, https://github.com/rionzz-inc/pyutilbox/issues
Project-URL: repository, https://github.com/rionzz-inc/pyutilbox
Keywords: Python envutil loader,django configuration loader,flask envutil loader
Classifier: Programming Language :: Python :: 3
Classifier: License :: OSI Approved :: MIT License
Classifier: Operating System :: OS Independent
Requires-Python: >=3.0
